pypkgs_ms/__init__.py
pypkgs_ms/pypkgs_ms.py
pypkgs_ms-0.1.0.dist-info/LICENSE
pypkgs_ms-0.1.0.dist-info/WHEEL
pypkgs_ms-0.1.0.dist-info/METADATA
pypkgs_ms-0.1.0.dist-info/RECORD
